geopandas-stubs/METADATA.toml
geopandas-stubs/__init__.pyi
geopandas-stubs/_config.pyi
geopandas-stubs/_decorator.pyi
geopandas-stubs/_exports.pyi
geopandas-stubs/accessors.pyi
geopandas-stubs/array.pyi
geopandas-stubs/base.pyi
geopandas-stubs/explore.pyi
geopandas-stubs/geodataframe.pyi
geopandas-stubs/geoseries.pyi
geopandas-stubs/plotting.pyi
geopandas-stubs/py.typed
geopandas-stubs/sindex.pyi
geopandas-stubs/testing.pyi
geopandas-stubs/io/__init__.pyi
geopandas-stubs/io/_geoarrow.pyi
geopandas-stubs/io/arrow.pyi
geopandas-stubs/io/file.pyi
geopandas-stubs/io/sql.pyi
geopandas-stubs/tools/__init__.pyi
geopandas-stubs/tools/_show_versions.pyi
geopandas-stubs/tools/clip.pyi
geopandas-stubs/tools/geocoding.pyi
geopandas-stubs/tools/hilbert_curve.pyi
geopandas-stubs/tools/overlay.pyi
geopandas-stubs/tools/sjoin.pyi
geopandas-stubs/tools/util.pyi
types_geopandas-1.1.2.20260120.dist-info/licenses/LICENSE
types_geopandas-1.1.2.20260120.dist-info/METADATA
types_geopandas-1.1.2.20260120.dist-info/WHEEL
types_geopandas-1.1.2.20260120.dist-info/top_level.txt
types_geopandas-1.1.2.20260120.dist-info/RECORD
